RKPairip/ANSI_COLORS.py
RKPairip/CLI.py
RKPairip/MODULES.py
RKPairip/RK_Pairip.py
RKPairip/__init__.py
RKPairip/Patch/Fix_Dex.py
RKPairip/Patch/Flutter_SO.py
RKPairip/Patch/Manifest_Patch.py
RKPairip/Patch/Other_Patch.py
RKPairip/Patch/Pairip_CoreX.py
RKPairip/Patch/Smali_Patch.py
RKPairip/Patch/__init__.py
RKPairip/Utils/Anti_Splits.py
RKPairip/Utils/CRC.py
RKPairip/Utils/Credits.py
RKPairip/Utils/Decompile_Compile.py
RKPairip/Utils/Extract.py
RKPairip/Utils/Files_Check.py
RKPairip/Utils/Scan.py
RKPairip/Utils/__init__.py
RKPairip/Utils/Files/Objectlogger.smali
RKPairip/Utils/Files/__init__.py
RKPairip/Utils/Files/lib_Pairip_CoreX.so
pairip-4.7.dist-info/licenses/LICENSE
pairip-4.7.dist-info/METADATA
pairip-4.7.dist-info/WHEEL
pairip-4.7.dist-info/entry_points.txt
pairip-4.7.dist-info/top_level.txt
pairip-4.7.dist-info/RECORD
