Metadata-Version: 2.4
Name: Pairip
Version: 4.7
Summary: Smali Patcher ( Recover String & Rebuild Apk )
Author-email: RK_TECHNO_INDIA <TechnoIndian786@gmail.com>
License: MIT
Project-URL: Homepage, https://github.com/TechnoIndian/RKPairip
Project-URL: Repository, https://github.com/TechnoIndian/RKPairip.git
Project-URL: Issues, https://github.com/TechnoIndian/RKPairip/issues
Keywords: RKPairip
Classifier: License :: OSI Approved :: MIT License
Classifier: Operating System :: OS Independent
Classifier: Programming Language :: Python :: 3
Requires-Python: >=3.12
License-File: LICENSE
Requires-Dist: requests
Requires-Dist: multiprocess
Dynamic: license-file
